subpr/__init__.py
subpr/__main__.py
subpr/compile.py
subpr/lib.py
subpr-0.0.4.dist-info/LICENSE
subpr-0.0.4.dist-info/METADATA
subpr-0.0.4.dist-info/WHEEL
subpr-0.0.4.dist-info/top_level.txt
subpr-0.0.4.dist-info/RECORD
