Metadata-Version: 2.1
Name: subpr
Version: 0.0.4
Summary: subprocess.run & os.chdir python shell libs (shell/exec/load/compile)
Home-page: https://github.com/FarAway6834/SubprunShell
Author: du7ec
Author-email: dutec6834@gmail.com
Keywords: subpr
Classifier: Programming Language :: Python :: 3.6
Classifier: Programming Language :: Python :: 3.7
Classifier: Programming Language :: Python :: 3.8
Classifier: Programming Language :: Python :: 3.9
Classifier: Programming Language :: Python :: 3.10
Classifier: Programming Language :: Python :: 3.11
Classifier: Programming Language :: Python :: 3.12
Classifier: Programming Language :: Python :: 3.13
Classifier: Programming Language :: Python :: 3.14
Requires-Python: >=3.6
License-File: LICENSE
Requires-Dist: martialLaw
